__init__.py
python_code_changed/__init__.py
python_code_changed/ast_utils.py
python_code_changed/cli.py
python_code_changed/helpers_logic.py
python_code_changed/helpers_trivial.py
python_code_changed-0.4.0.dist-info/licenses/LICENSE
python_code_changed-0.4.0.dist-info/METADATA
python_code_changed-0.4.0.dist-info/WHEEL
python_code_changed-0.4.0.dist-info/entry_points.txt
python_code_changed-0.4.0.dist-info/top_level.txt
python_code_changed-0.4.0.dist-info/RECORD
