Metadata-Version: 2.4
Name: python_code_changed
Version: 0.4.0
Summary: A Python project to detect real code changes.
Author-email: Dean Godfree <deangodfree@outlook.com>
License: MIT License
Project-URL: Homepage, https://github.com/DeanGodfreeItalia/python_code_changed
Project-URL: Repository, https://github.com/DeanGodfreeItalia/python_code_changed
Requires-Python: >=3.12
License-File: LICENSE
Requires-Dist: typer>=0.16.0
Provides-Extra: dev
Requires-Dist: ruff>=0.4.4; extra == "dev"
Requires-Dist: black>=24.4.0; extra == "dev"
Requires-Dist: pytest>=8.4.1; extra == "dev"
Requires-Dist: typer>=0.16.0; extra == "dev"
Requires-Dist: isort>=5.13.2; extra == "dev"
Requires-Dist: pip-audit>=2.7.2; extra == "dev"
Requires-Dist: pytest-cov>=5.0.0; extra == "dev"
Requires-Dist: mypy>=1.10.0; extra == "dev"
Requires-Dist: hatch>=1.9.0; extra == "dev"
Requires-Dist: toml-cli>=0.8.1; extra == "dev"
Dynamic: license-file
